pybip39-0.1.0.dist-info/METADATA
pybip39-0.1.0.dist-info/WHEEL
pybip39-0.1.0.dist-info/license_files/LICENSE
pybip39.libs/libgcc_s-0c8db386.so.1
pybip39/__init__.py
pybip39/__init__.pyi
pybip39/py.typed
pybip39/pybip39.abi3.so
pybip39-0.1.0.dist-info/RECORD
