Metadata-Version: 2.1
Name: pybip39
Version: 0.1.0
Classifier: Programming Language :: Rust
Classifier: Programming Language :: Python :: Implementation :: CPython
License-File: LICENSE
Summary: Python binding to tiny-bip39, the Rust case conversion library
Author-email: kevinheavey <kevinheavey123@gmail.com>
Requires-Python: >=3.7
Project-URL: documentation, https://kevinheavey.github.io/pybip39/
Project-URL: homepage, https://github.com/kevinheavey/pybip39
Project-URL: changelog, https://github.com/kevinheavey/pybip39/blob/main/CHANGELOG.md
Project-URL: repository, https://github.com/kevinheavey/pybip39
